featureformatter/__init__.py
featureformatter/AudioFormatter/__init__.py
featureformatter/AudioFormatter/wavfile.py
featureformatter/ObjectFormatter/__init__.py
feature_formatter-0.4.3.dist-info/LICENSE
feature_formatter-0.4.3.dist-info/METADATA
feature_formatter-0.4.3.dist-info/WHEEL
feature_formatter-0.4.3.dist-info/top_level.txt
feature_formatter-0.4.3.dist-info/RECORD
