Metadata-Version: 2.1
Name: feature-formatter
Version: 0.4.3
Summary: A smart formatter to translate raw text into readable text
Home-page: 
Author: Bob Zhou
Author-email: bob.zhou@ef.com
License: MIT
Keywords: text audio formatter
Classifier: Development Status :: 3 - Alpha
Classifier: Intended Audience :: Developers
Classifier: License :: OSI Approved :: MIT License
Classifier: Programming Language :: Python :: 3 :: Only
Classifier: Programming Language :: Python :: 3.5
Classifier: Programming Language :: Python :: 3.6
Classifier: Programming Language :: Python :: 3.7
Requires-Python: >=3.5, <4
License-File: LICENSE
Requires-Dist: num2words
Requires-Dist: numpy
